vviewer/__init__.py
vviewer/main.py
vviewer/reader.py
vviewer/utils.py
vviewer-0.1.1.dist-info/LICENSE
vviewer-0.1.1.dist-info/METADATA
vviewer-0.1.1.dist-info/WHEEL
vviewer-0.1.1.dist-info/entry_points.txt
vviewer-0.1.1.dist-info/top_level.txt
vviewer-0.1.1.dist-info/RECORD
