Metadata-Version: 2.1
Name: vviewer
Version: 0.1.1
Summary: viewer for text data
Home-page: https://github.com/t2y/vviewer
Author: Tetsuya Morimoto
Author-email: tetsuya.morimoto@gmail.com 
License: Apache License 2.0
Keywords: vertical,viewer,csv
Platform: unix
Platform: linux
Platform: osx
Platform: windows
Classifier: License :: OSI Approved :: Apache Software License
Classifier: Development Status :: 4 - Beta
Classifier: Intended Audience :: Developers
Classifier: Operating System :: OS Independent
Classifier: Programming Language :: Python :: 3.6
Classifier: Programming Language :: Python :: 3.7
Classifier: Programming Language :: Python :: Implementation :: CPython
Classifier: Programming Language :: Python :: Implementation :: PyPy
Classifier: Topic :: Software Development :: Libraries
Classifier: Environment :: Console
Classifier: Topic :: Utilities
